pytest_db/__init__.py
pytest_db/db_client_factory.py
pytest_db/logger.py
pytest_db/plugin.py
pytest_db/utils.py
pytest_db/clients/__init__.py
pytest_db/clients/base_client.py
pytest_db/clients/default_client.py
pytest_db/clients/es_client.py
pytest_db/clients/local_file_client.py
pytest_db_plugin-0.0.0.0.0.2.dist-info/METADATA
pytest_db_plugin-0.0.0.0.0.2.dist-info/WHEEL
pytest_db_plugin-0.0.0.0.0.2.dist-info/entry_points.txt
pytest_db_plugin-0.0.0.0.0.2.dist-info/top_level.txt
pytest_db_plugin-0.0.0.0.0.2.dist-info/RECORD
