Metadata-Version: 2.1
Name: pytest-db-plugin
Version: 0.0.0.0.0.2
Summary: UNKNOWN
Home-page: UNKNOWN
Author: Avi Naftalis
Author-email: avin@hailo.ai
License: UNKNOWN
Platform: UNKNOWN
Classifier: Framework :: Pytest
Classifier: Programming Language :: Python
Classifier: Programming Language :: Python :: 3
Classifier: Programming Language :: Python :: 3.6
Classifier: Programming Language :: Python :: 3.7
Classifier: Programming Language :: Python :: 3.8
Classifier: Programming Language :: Python :: 3 :: Only
Requires-Python: >=3.6
Requires-Dist: pytest (>=5.0)
Provides-Extra: es
Requires-Dist: elasticsearch ; extra == 'es'
